Metadata-Version: 1.0
Name: distributions-dangat
Version: 0.1
Summary: Gaussian and Binomial distributions
Home-page: UNKNOWN
Author: Daniel Gaitan
Author-email: danielgaitanforero@gmail.com
License: MIT
Platform: UNKNOWN
